fundamentum_edge_proto/__init__.py
fundamentum_edge_proto/actions_pb2.py
fundamentum_edge_proto/actions_pb2.pyi
fundamentum_edge_proto/actions_pb2_grpc.py
fundamentum_edge_proto/actions_pb2_grpc.pyi
fundamentum_edge_proto/configuration_pb2.py
fundamentum_edge_proto/configuration_pb2.pyi
fundamentum_edge_proto/configuration_pb2_grpc.py
fundamentum_edge_proto/configuration_pb2_grpc.pyi
fundamentum_edge_proto/provisioning_pb2.py
fundamentum_edge_proto/provisioning_pb2.pyi
fundamentum_edge_proto/provisioning_pb2_grpc.py
fundamentum_edge_proto/provisioning_pb2_grpc.pyi
fundamentum_edge_proto/py.typed
fundamentum_edge_proto/qos_pb2.py
fundamentum_edge_proto/qos_pb2.pyi
fundamentum_edge_proto/qos_pb2_grpc.py
fundamentum_edge_proto/qos_pb2_grpc.pyi
fundamentum_edge_proto/states_pb2.py
fundamentum_edge_proto/states_pb2.pyi
fundamentum_edge_proto/states_pb2_grpc.py
fundamentum_edge_proto/states_pb2_grpc.pyi
fundamentum_edge_proto/telemetry_pb2.py
fundamentum_edge_proto/telemetry_pb2.pyi
fundamentum_edge_proto/telemetry_pb2_grpc.py
fundamentum_edge_proto/telemetry_pb2_grpc.pyi
fundamentum_edge_proto/typed_stubs.py
fundamentum_edge_proto/update_pb2.py
fundamentum_edge_proto/update_pb2.pyi
fundamentum_edge_proto/update_pb2_grpc.py
fundamentum_edge_proto/update_pb2_grpc.pyi
fundamentum_edge_proto-1.6.1.dist-info/METADATA
fundamentum_edge_proto-1.6.1.dist-info/WHEEL
fundamentum_edge_proto-1.6.1.dist-info/licenses/LICENSE
fundamentum_edge_proto-1.6.1.dist-info/RECORD
