Metadata-Version: 2.4
Name: fundamentum-edge-proto
Version: 1.6.1
Summary: fundamentum-edge protobufs
Project-URL: repository, https://bitbucket.org/amotus/fundamentum-edge-proto-python
Author-email: Alex Sirois <asirois@dimonoff.com>, Jonathan Chouinard <jchouinard@dimonoff.com>
License:                                  Apache License
License-File: LICENSE
Requires-Python: >=3.10
Requires-Dist: grpcio~=1.63
Requires-Dist: protobuf~=4.25.3
